pystand_cli/__init__.py
pystand_cli/cli.py
pystand_cli-0.1.0.dist-info/LICENSE
pystand_cli-0.1.0.dist-info/METADATA
pystand_cli-0.1.0.dist-info/WHEEL
pystand_cli-0.1.0.dist-info/entry_points.txt
pystand_cli-0.1.0.dist-info/RECORD
