Metadata-Version: 2.3
Name: pystand-cli
Version: 0.1.0
Summary: PyStand打包命令行工具
License: MIT
Author: ASTWY
Author-email: astwy@outlook.com
Requires-Python: >=3.9
Classifier: License :: OSI Approved :: MIT License
Classifier: Programming Language :: Python :: 3
Classifier: Programming Language :: Python :: 3.9
Classifier: Programming Language :: Python :: 3.10
Classifier: Programming Language :: Python :: 3.11
Classifier: Programming Language :: Python :: 3.12
Classifier: Programming Language :: Python :: 3.13
Requires-Dist: click (>=8.1.8,<9.0.0)
Requires-Dist: httpx (>=0.28.1,<0.29.0)
